<annotation><folder>VOC2007</folder><filename>1172</filename><size><width>1020</width><height>628</height><depth>3</depth></size><object><name>B52</name><bndbox><xmin>101</xmin><ymin>357</ymin><xmax>180</xmax><ymax>428</ymax></bndbox></object><object><name>B52</name><bndbox><xmin>276</xmin><ymin>347</ymin><xmax>357</xmax><ymax>417</ymax></bndbox></object><object><name>B52</name><bndbox><xmin>640</xmin><ymin>324</ymin><xmax>720</xmax><ymax>394</ymax></bndbox></object><object><name>B52</name><bndbox><xmin>815</xmin><ymin>313</ymin><xmax>895</xmax><ymax>384</ymax></bndbox></object></annotation>