<annotation><folder>VOC2007</folder><filename>315</filename><size><width>5184</width><height>3456</height><depth>3</depth></size><object><name>J20</name><bndbox><xmin>977</xmin><ymin>1592</ymin><xmax>1238</xmax><ymax>1869</ymax></bndbox></object><object><name>J20</name><bndbox><xmin>1781</xmin><ymin>2034</ymin><xmax>2028</xmax><ymax>2286</ymax></bndbox></object><object><name>J20</name><bndbox><xmin>2554</xmin><ymin>2439</ymin><xmax>2800</xmax><ymax>2679</ymax></bndbox></object><object><name>J20</name><bndbox><xmin>2924</xmin><ymin>2025</ymin><xmax>3180</xmax><ymax>2284</ymax></bndbox></object><object><name>J20</name><bndbox><xmin>3349</xmin><ymin>1552</ymin><xmax>3626</xmax><ymax>1841</ymax></bndbox></object></annotation>